README.md
setup.py
./etc/client.cfg
./etc/server.cfg
./etc/user_file
tools/ytvpn
ytvpn/__init__.py
ytvpn/ytvpn.py
ytvpn.egg-info/PKG-INFO
ytvpn.egg-info/SOURCES.txt
ytvpn.egg-info/dependency_links.txt
ytvpn.egg-info/requires.txt
ytvpn.egg-info/top_level.txt
ytvpn/client/__init__.py
ytvpn/client/client.py
ytvpn/client/client_protocol.py
ytvpn/client/conf.py
ytvpn/client/data_handler.py
ytvpn/client/inner_worker.py
ytvpn/client/outer_worker.py
ytvpn/client/worker_manager.py
ytvpn/common/__init__.py
ytvpn/common/acceptor.py
ytvpn/common/connector.py
ytvpn/common/data_handler.py
ytvpn/common/epoll_recever.py
ytvpn/common/forward_data.py
ytvpn/common/forward_event.py
ytvpn/common/if_tun.py
ytvpn/common/ioctl_def.py
ytvpn/common/ip_protocol_handler.py
ytvpn/common/protocol_handler.py
ytvpn/common/ring_buffer.py
ytvpn/common/rsa_handler.py
ytvpn/common/tools.py
ytvpn/common/tun_connector.py
ytvpn/server/__init__.py
ytvpn/server/conf.py
ytvpn/server/data_handler.py
ytvpn/server/dhcp_manager.py
ytvpn/server/inner_worker.py
ytvpn/server/outer_worker.py
ytvpn/server/server.py
ytvpn/server/user_pass.py
ytvpn/server/worker_manager.py