Metadata-Version: 1.0
Name: ytvpn
Version: 1.0.0
Summary: an opensource vpn tool
Home-page: https://github.com/cao19881125/ytvpn.git
Author: yuntao.cao
Author-email: yuntao.cao@nocsys.com.cn
License: MIT
Keywords: vpn
Platform: any
